pytorrentsearch/VERSION
pytorrentsearch/__init__.py
pytorrentsearch/__main__.py
pytorrentsearch/base.py
pytorrentsearch/cli.py
pytorrentsearch/miner.py
pytorrentsearch/utils.py
pytorrentsearch/search/__init__.py
pytorrentsearch/search/duckduckgo.py
pytorrentsearch/search/google.py
pytorrentsearch/search/yandex.py
pytorrentsearch-0.3.0.dist-info/METADATA
pytorrentsearch-0.3.0.dist-info/WHEEL
pytorrentsearch-0.3.0.dist-info/entry_points.txt
pytorrentsearch-0.3.0.dist-info/licenses/LICENSE
pytorrentsearch-0.3.0.dist-info/RECORD
