Metadata-Version: 2.4
Name: pytorrentsearch
Version: 0.3.0
Summary: No distraction way to find torrents
Project-URL: Homepage, https://github.com/lucasew/pytorrentsearch
Project-URL: Repository, https://github.com/lucasew/pytorrentsearch
License: MIT
License-File: LICENSE
Requires-Python: >=3.9
